links_kernel/__init__.py
links_kernel/__main__.py
links_kernel/install.py
links_kernel/links_kernel.py
linkskernel-0.0.7.dist-info/LICENSE
linkskernel-0.0.7.dist-info/METADATA
linkskernel-0.0.7.dist-info/WHEEL
linkskernel-0.0.7.dist-info/top_level.txt
linkskernel-0.0.7.dist-info/RECORD
